README.md
setup.py
pip_show/__init__.py
pip_show/main.py
pip_show_json.egg-info/PKG-INFO
pip_show_json.egg-info/SOURCES.txt
pip_show_json.egg-info/dependency_links.txt
pip_show_json.egg-info/entry_points.txt
pip_show_json.egg-info/top_level.txt