Metadata-Version: 2.1
Name: pip-show-json
Version: 1.0.3
Summary: Show JSON metadata for an uninstalled pip package
Home-page: https://github.com/talwrii/pip-show
Author: readwithai
Author-email: talwrii@gmail.com
License: MIT
